{
    "name": "UserInfo",
    "fields": [
        {
            "fieldName": "phone",
            "fieldType": "String"
        },
        {
            "fieldName": "mobilePhone",
            "fieldType": "String"
        },
        {
            "fieldName": "emailFlag",
            "fieldType": "Boolean"
        },
        {
            "fieldName": "smsFlag",
            "fieldType": "Boolean"
        },
        {
            "fieldName": "birthDate",
            "fieldType": "LocalDate"
        },
        {
            "fieldName": "gender",
            "fieldType": "Gender",
            "fieldValues": "MALE,FEMALE,OTHER"
        }
    ],
    "relationships": [
        {
            "relationshipType": "one-to-one",
            "otherEntityName": "user",
            "otherEntityRelationshipName": "userInfo",
            "relationshipName": "user",
            "otherEntityField": "login",
            "ownerSide": true
        }
    ],
    "changelogDate": "20190726020403",
    "entityTableName": "user_info",
    "dto": "no",
    "pagination": "no",
    "service": "serviceClass",
    "jpaMetamodelFiltering": true,
    "fluentMethods": true,
    "clientRootFolder": "",
    "applications": "*"
}
